async_orchestrator/__init__.py
async_orchestrator/async_orchestrator.py
async_orchestrator/auth.py
async_orchestrator/client.py
async_orchestrator/resource.py
orchestrator/__init__.py
orchestrator/auth.py
orchestrator/client.py
orchestrator/orchestrator.py
orchestrator/orchestrator_resource.py
uipath_orchestrator-0.7.2.dist-info/LICENSE
uipath_orchestrator-0.7.2.dist-info/METADATA
uipath_orchestrator-0.7.2.dist-info/WHEEL
uipath_orchestrator-0.7.2.dist-info/top_level.txt
uipath_orchestrator-0.7.2.dist-info/RECORD
